cappy/__init__.py
cappy/cappy.py
cappy-1.2.3.dist-info/DESCRIPTION.rst
cappy-1.2.3.dist-info/METADATA
cappy-1.2.3.dist-info/RECORD
cappy-1.2.3.dist-info/WHEEL
cappy-1.2.3.dist-info/entry_points.txt
cappy-1.2.3.dist-info/metadata.json
cappy-1.2.3.dist-info/top_level.txt
