Metadata-Version: 2.0
Name: cappy
Version: 1.2.3
Summary: A simple file based python poxy
Home-page: https://github.com/CompileInc/cappy
Author: Compile Inc
Author-email: dev@compile.com
License: MIT
Download-URL: https://github.com/CompileInc/cappy/archive/v1.2.3.tar.gz
Keywords: cappy,proxy,http
Platform: UNKNOWN
Requires-Dist: fire (>=0.1)
Requires-Dist: requests[security] (>=2.18)
